python_introspection/__init__.py
python_introspection/__main__.py
python_introspection/_cli.py
python_introspection/scripts/__init__.py
python_introspection/scripts/generate-build-details.py
python_introspection-0.1.0.post1.dist-info/licenses/LICENSE
python_introspection-0.1.0.post1.dist-info/WHEEL
python_introspection-0.1.0.post1.dist-info/METADATA
python_introspection-0.1.0.post1.dist-info/RECORD
